{
  "db_name": "PostgreSQL",
  "query": "\n            INSERT INTO admins (id, phone, password_hash, role, store_id, created_at, updated_at)\n            VALUES ($1, $2, $3, $4, $5, $6, $7)\n            RETURNING id, phone, password_hash, role, store_id, created_at, updated_at\n            ",
  "describe": {
    "columns": [
      {
        "ordinal": 0,
        "name": "id",
        "type_info": "Varchar"
      },
      {
        "ordinal": 1,
        "name": "phone",
        "type_info": "Varchar"
      },
      {
        "ordinal": 2,
        "name": "password_hash",
        "type_info": "Varchar"
      },
      {
        "ordinal": 3,
        "name": "role",
        "type_info": "Varchar"
      },
      {
        "ordinal": 4,
        "name": "store_id",
        "type_info": "Varchar"
      },
      {
        "ordinal": 5,
        "name": "created_at",
        "type_info": "Timestamptz"
      },
      {
        "ordinal": 6,
        "name": "updated_at",
        "type_info": "Timestamptz"
      }
    ],
    "parameters": {
      "Left": [
        "Varchar",
        "Varchar",
        "Varchar",
        "Varchar",
        "Varchar",
        "Timestamptz",
        "Timestamptz"
      ]
    },
    "nullable": [
      false,
      false,
      false,
      false,
      true,
      false,
      false
    ]
  },
  "hash": "03a4852a882eedb9c96ca2a9a9a1163ed3d26f4e7e6d1c30acd12b8aabfa71b4"
}
